<?xml version="1.0" encoding="UTF-8" standalone="no" ?>
<tt xmlns="http://www.w3.org/ns/ttml" xmlns:ttp="http://www.w3.org/ns/ttml#parameter" ttp:dropMode="nonDrop" ttp:frameRate="30" ttp:frameRateMultiplier="1000 1001" ttp:timeBase="smpte" xmlns:m608="http://www.smpte-ra.org/schemas/2052-1/2010/smpte-tt#cea608" xmlns:smpte="http://www.smpte-ra.org/schemas/2052-1/2010/smpte-tt" xmlns:ttm="http://www.w3.org/ns/ttml#metadata" xmlns:tts="http://www.w3.org/ns/ttml#styling">

  <head>
    <styling>
      <style tts:color="white" tts:fontFamily="monospace" tts:fontWeight="normal" tts:textAlign="left" xml:id="basic"/>
    </styling>
    <layout>
      <region tts:backgroundColor="transparent" xml:id="pop1"/>
      <region tts:backgroundColor="transparent" xml:id="paint"/>
      <region tts:backgroundColor="transparent" xml:id="rollup2"/>
      <region tts:backgroundColor="transparent" xml:id="rollup3"/>
      <region tts:backgroundColor="transparent" xml:id="rollup4"/>
    </layout>
    <metadata/>
    <smpte:information m608:captionService="F1C1CC" m608:channel="cc1"/>
  </head>

  <body>
    <div>
      <p begin="00:01:21:08" end="00:01:50:03" region="pop1" style="basic" tts:origin="10% 84.664000000000001%">
        <style/>
        <span>no speaking
          <style tts:backgroundColor="#000000FF" tts:fontSize="18px"/>
        </span>
      </p>
      <p begin="00:01:50:03" end="00:01:55:15" region="pop1" style="basic" tts:origin="10% 84.664000000000001%">
        <style/>
        <span>speaking
          <style tts:backgroundColor="#000000FF" tts:fontSize="18px"/>
        </span>
      </p>
      <p begin="00:01:55:15" end="00:02:31:17" region="pop1" style="basic" tts:origin="10% 84.664000000000001%">
        <style/>
        <span>no speaking
          <style tts:backgroundColor="#000000FF" tts:fontSize="18px"/>
        </span>
      </p>
      <p begin="00:02:31:17" end="00:02:39:01" region="pop1" style="basic" tts:origin="10% 84.664000000000001%">
        <style/>
        <span>speaking
          <style tts:backgroundColor="#000000FF" tts:fontSize="18px"/>
        </span>
      </p>
      <p begin="00:02:39:01" end="00:03:27:15" region="pop1" style="basic" tts:origin="10% 84.664000000000001%">
        <style/>
        <span>no speaking
          <style tts:backgroundColor="#000000FF" tts:fontSize="18px"/>
        </span>
      </p>
      <p begin="00:03:27:15" end="00:03:46:14" region="pop1" style="basic" tts:origin="10% 84.664000000000001%">
        <style/>
        <span>speaking
          <style tts:backgroundColor="#000000FF" tts:fontSize="18px"/>
        </span>
      </p>
      <p begin="00:03:46:14" end="00:04:38:25" region="pop1" style="basic" tts:origin="10% 84.664000000000001%">
        <style/>
        <span>no speaking 
          <style tts:backgroundColor="#000000FF" tts:fontSize="18px"/>
        </span>
      </p>
      <p begin="00:04:38:25" end="00:04:52:14" region="pop1" style="basic" tts:origin="10% 84.664000000000001%">
        <style/>
        <span>speaking
          <style tts:backgroundColor="#000000FF" tts:fontSize="18px"/>
        </span>
      </p>
      <p begin="00:04:52:14" end="00:05:21:27" region="pop1" style="basic" tts:origin="10% 84.664000000000001%">
        <style/>
        <span>no speaking
          <style tts:backgroundColor="#000000FF" tts:fontSize="18px"/>
        </span>
      </p>
      <p begin="00:05:21:27" end="00:05:39:22" region="pop1" style="basic" tts:origin="10% 84.664000000000001%">
        <style/>
        <span>speaking
          <style tts:backgroundColor="#000000FF" tts:fontSize="18px"/>
        </span>
      </p>
    </div>
  </body>

</tt>
